{
  "experiment-list": [
    {
      "test_size": 200,
      "pool_size": 500,
      "labelled_size": 200,
      "OOD_ratio": 0.1,
      "oracle_stepsize": 50,
      "oracle_steps": 2,
      "epochs": 1,
      "batch_size": 50,
      "oracles": ["least confidence"],
      "weight_decay": 1e-5,
      "metric": "f1",
      "model_name": "small_gen_odin_res",
      "similarity": "E",
      "include_bn": false,
      "nesterov": false,
      "lr": 0.1,
      "momentum": 0.9
    }
  ],
  "in_dist_data": ["Cifar10"],
  "ood_data": ["MNIST"]
}
